sd/__init__.py
sd/agent/__init__.py
sd/agent/agent_type.py
sd/communication/__init__.py
sd/communication/client/__init__.py
sd/communication/client/connection/__init__.py
sd/communication/client/connection/connection.py
sd/communication/client/connection/interface.py
sd/communication/client/protocol/__init__.py
sd/communication/client/protocol/interface.py
sd/communication/client/protocol/protocol.py
sd/communication/server/__init__.py
sd/communication/server/protocol/__init__.py
sd/communication/server/protocol/function_code.py
sd/communication/server/protocol/interface.py
sd/communication/server/protocol/protocol.py
sd/data/__init__.py
sd/data/common/__init__.py
sd/data/common/enum/__init__.py
sd/example/DataExample.py
sd/example/DemoStrategy.py
sd/example/FutureAbritrate.py
sd/example/__init__.py
sd/example/config.py
sd/example/logconfig.py
sd/exception/__init__.py
sd/exception/exception.py
sd/scripts/__init__.py
sd/scripts/server/__init__.py
sd/scripts/server/server.py
sd/strategy/__init__.py
sd/strategy/interface.py
sd/strategy/request.py
sd/strategy/stragety.py
sd/strategy/bean/__init__.py
sd/strategy/bean/bean.py
sd/strategy/bean/databean.py
sd/strategy/bean/datatype.py
sd/strategy/bean/enum/__init__.py
sd/strategy/client/__init__.py
sd/strategy/client/client.py
sd/strategy/client/interface.py
sd/utils/__init__.py
sd/utils/bean.py
sd/utils/enum.py
sd/utils/io/__init__.py
sd/utils/io/io.py
strategy_sdk-1.0.9.dist-info/DESCRIPTION.rst
strategy_sdk-1.0.9.dist-info/METADATA
strategy_sdk-1.0.9.dist-info/RECORD
strategy_sdk-1.0.9.dist-info/WHEEL
strategy_sdk-1.0.9.dist-info/metadata.json
strategy_sdk-1.0.9.dist-info/top_level.txt
strategy_sdk-1.0.9.dist-info/zip-safe
