Metadata-Version: 2.0
Name: strategy-sdk
Version: 1.0.9
Summary: this is a python client sdk for strategy access
Home-page: https://pypi.python.org/pypi/strategy-sdk
Author: Yonka Fang
Author-email: yonka.fang@foxmail.com
License: MIT
Keywords: python strategy sdk client
Platform: UNKNOWN
Classifier: License :: OSI Approved :: MIT License
Classifier: Programming Language :: Python
Classifier: Intended Audience :: Developers
Classifier: Operating System :: OS Independent
Requires: protobuf
Requires: futures
Requires-Dist: futures
Requires-Dist: protobuf
